AIsketcher/__init__.py
AIsketcher/modelPipe.py
AIsketcher-0.0.0.4.dist-info/METADATA
AIsketcher-0.0.0.4.dist-info/WHEEL
AIsketcher-0.0.0.4.dist-info/top_level.txt
AIsketcher-0.0.0.4.dist-info/RECORD
