Metadata-Version: 2.1
Name: AIsketcher
Version: 0.0.0.4
Summary: Text-to-image generation using Huggingface stable diffusion ControlNet conditioning and AWS Translate's prompt translation function package
Home-page: https://github.com/hyeonsangjeon/AIsketcher
Author: hyeonsangjeon
Author-email: wingnut0310@gmail.com
License: UNKNOWN
Platform: UNKNOWN
Classifier: Programming Language :: Python :: 3.9
Classifier: License :: OSI Approved :: MIT License
Classifier: Operating System :: OS Independent
Requires-Dist: opencv-contrib-python
Requires-Dist: diffusers
Requires-Dist: transformers
Requires-Dist: boto3
